gnssmultipath/BroadNavPositionEstimator.py
gnssmultipath/GNSSPositionEstimator.py
gnssmultipath/GNSS_MultipathAnalysis.py
gnssmultipath/Geodetic_functions.py
gnssmultipath/PickleHandler.py
gnssmultipath/PreciseSatCoords.py
gnssmultipath/RinexNav.py
gnssmultipath/SP3Interpolator.py
gnssmultipath/SP3PositionEstimator.py
gnssmultipath/SP3Reader.py
gnssmultipath/SatelliteEphemerisToECEF.py
gnssmultipath/StatisticalAnalysis.py
gnssmultipath/__init__.py
gnssmultipath/computeDelayStats.py
gnssmultipath/computeSatElevAzimuth_fromNav.py
gnssmultipath/createCSVfile.py
gnssmultipath/detectClockJumps.py
gnssmultipath/detectCycleSlips.py
gnssmultipath/estimateSignalDelays.py
gnssmultipath/getLLISlipPeriods.py
gnssmultipath/make_polarplot.py
gnssmultipath/make_polarplot_dont_use_TEX.py
gnssmultipath/plotResults.py
gnssmultipath/readRinexObs.py
gnssmultipath/read_SP3Nav.py
gnssmultipath/signalAnalysis.py
gnssmultipath/writeOutputFile.py
gnssmultipath-1.6.1.dist-info/licenses/LICENSE.md
gnssmultipath-1.6.1.dist-info/METADATA
gnssmultipath-1.6.1.dist-info/WHEEL
gnssmultipath-1.6.1.dist-info/top_level.txt
gnssmultipath-1.6.1.dist-info/RECORD
