Metadata-Version: 2.4
Name: gnssmultipath
Version: 1.6.1
Summary: A python software that provides comprehensive solutions for GNSS multipath analysis.
Author-email: Per Helge Aarnes <per.helge.aarnes@gmail.com>
Maintainer-email: Per Helge Aarnes <per.helge.aarnes@gmail.com>
License: MIT
Project-URL: Homepage, https://github.com/paarnes/GNSS_Multipath_Analysis_Software
Project-URL: Bug Tracker, https://github.com/paarnes/GNSS_Multipath_Analysis_Software/issues
Keywords: GNSS,multipath,analytics,gps,glonass,galileo,beidou,rinex,sp3,snr,position-estimation
Classifier: Programming Language :: Python :: 3.10
Classifier: Programming Language :: Python :: 3.11
Classifier: Programming Language :: Python :: 3.12
Classifier: Programming Language :: Python :: 3.13
Classifier: License :: OSI Approved :: MIT License
Classifier: Operating System :: OS Independent
Requires-Python: >=3.10
License-File: LICENSE.md
Requires-Dist: matplotlib==3.9.2
Requires-Dist: numpy==2.1.0
Requires-Dist: pandas==2.3.0
Requires-Dist: tqdm==4.66.5
Requires-Dist: zstandard==0.23.0
Requires-Dist: pyproj==3.7.1
Dynamic: license-file
